anknote/__init__.py
anknote/config.py
anknote/main.py
anknote/io/__init__.py
anknote/io/card.py
anknote/io/gather.py
anknote/io/write.py
anknote-0.1.1.dist-info/METADATA
anknote-0.1.1.dist-info/WHEEL
anknote-0.1.1.dist-info/entry_points.txt
anknote-0.1.1.dist-info/licenses/LICENSE
anknote-0.1.1.dist-info/RECORD
