Metadata-Version: 2.4
Name: anknote
Version: 0.1.1
Summary: Generate Anki notes with LLMs.
Author-email: rayanramoul <raysamram@gmail.com>
License-File: LICENSE
Requires-Python: >=3.13
Requires-Dist: litellm>=1.70.0
Requires-Dist: loguru>=0.7.3
Requires-Dist: pydantic>=2.11.4
Requires-Dist: rich>=14.0.0
Provides-Extra: docs
Requires-Dist: mkdocs-autorefs==1.2.0; extra == 'docs'
Requires-Dist: mkdocs-gen-files==0.5.0; extra == 'docs'
Requires-Dist: mkdocs-get-deps==0.2.0; extra == 'docs'
Requires-Dist: mkdocs-material-extensions==1.3.1; extra == 'docs'
Requires-Dist: mkdocs-material==9.5.41; extra == 'docs'
Requires-Dist: mkdocs-mermaid2-plugin==1.1.1; extra == 'docs'
Requires-Dist: mkdocs-same-dir; extra == 'docs'
Requires-Dist: mkdocs==1.6.1; extra == 'docs'
Requires-Dist: mkdocstrings-python==1.12.1; extra == 'docs'
Requires-Dist: mkdocstrings==0.26.2; extra == 'docs'
Requires-Dist: pymdown-extensions==10.11.2; extra == 'docs'
Provides-Extra: lint
Requires-Dist: mypy>=1.14.1; extra == 'lint'
Requires-Dist: pandas-stubs>=2.2.3.241126; extra == 'lint'
Requires-Dist: pre-commit>=4.0.1; extra == 'lint'
Requires-Dist: types-pyyaml>=6.0.12.20241230; extra == 'lint'
Requires-Dist: types-regex>=2024.11.6.20241221; extra == 'lint'
Requires-Dist: types-requests>=2.31.0.6; extra == 'lint'
Requires-Dist: types-tqdm>=4.67.0.20241221; extra == 'lint'
Provides-Extra: test
Requires-Dist: pytest>=6.2.4; extra == 'test'
